{
  "id": "grass",
  "symbol": "grass",
  "name": "Grass",
  "web_slug": "grass",
  "asset_platform_id": "solana",
  "platforms": {
    "solana": "Grass7B4RdKfBCjTKgSqnXkqjwiGvQyFbuSCUJr3XXjs"
  },
  "detail_platforms": {
    "solana": {
      "decimal_place": 9,
      "contract_address": "Grass7B4RdKfBCjTKgSqnXkqjwiGvQyFbuSCUJr3XXjs"
    }
  },
  "block_time_in_minutes": 0,
  "hashing_algorithm": null,
  "categories": [
    "Artificial Intelligence (AI)",
    "Solana Ecosystem",
    "DePIN",
    "Polychain Capital Portfolio"
  ],
  "preview_listing": false,
  "public_notice": null,
  "additional_notices": [],
  "description": {
    "en": ""
  },
  "links": {
    "homepage": [
      "https://grass.io/",
      "https://www.getgrass.io/"
    ],
    "whitepaper": "https://wynd-network.gitbook.io/grass-docs",
    "blockchain_site": [
      "https://solscan.io/token/Grass7B4RdKfBCjTKgSqnXkqjwiGvQyFbuSCUJr3XXjs",
      "https://platform.arkhamintelligence.com/explorer/token/grass"
    ],
    "official_forum_url": [
      "https://discord.gg/getgrass"
    ],
    "chat_url": [],
    "announcement_url": [],
    "snapshot_url": null,
    "twitter_screen_name": "grass",
    "facebook_username": "",
    "bitcointalk_thread_identifier": null,
    "telegram_channel_identifier": "",
    "subreddit_url": "https://www.reddit.com",
    "repos_url": {
      "github": [],
      "bitbucket": []
    }
  },
  "image": {
    "thumb": "https://coin-images.coingecko.com/coins/images/40094/thumb/Grass.jpg?1725697048",
    "small": "https://coin-images.coingecko.com/coins/images/40094/small/Grass.jpg?1725697048",
    "large": "https://coin-images.coingecko.com/coins/images/40094/large/Grass.jpg?1725697048"
  },
  "country_origin": "",
  "genesis_date": null,
  "contract_address": "Grass7B4RdKfBCjTKgSqnXkqjwiGvQyFbuSCUJr3XXjs",
  "sentiment_votes_up_percentage": 28.57,
  "sentiment_votes_down_percentage": 71.43,
  "watchlist_portfolio_users": 42140,
  "market_cap_rank": 174,
  "market_data": {
    "current_price": {
      "aed": 5.25,
      "ars": 1632.98,
      "aud": 2.2,
      "bch": 0.00311364,
      "bdt": 174.76,
      "bhd": 0.539113,
      "bmd": 1.43,
      "bnb": 0.00221556,
      "brl": 7.84,
      "btc": 1.361e-05,
      "cad": 1.96,
      "chf": 1.17,
      "clp": 1348.5,
      "cny": 10.28,
      "czk": 30.94,
      "dkk": 9.3,
      "dot": 0.396455,
      "eos": 2.797566,
      "eth": 0.00056636,
      "eur": 1.25,
      "gbp": 1.066,
      "gel": 3.89,
      "hkd": 11.22,
      "huf": 502.91,
      "idr": 23411,
      "ils": 4.96,
      "inr": 123.76,
      "jpy": 207.37,
      "krw": 1971.31,
      "kwd": 0.438061,
      "lkr": 429.32,
      "ltc": 0.01677847,
      "mmk": 2999.34,
      "mxn": 27.24,
      "myr": 6.09,
      "ngn": 2211.14,
      "nok": 14.28,
      "nzd": 2.38,
      "php": 81.94,
      "pkr": 405.17,
      "pln": 5.33,
      "rub": 112.23,
      "sar": 5.36,
      "sek": 13.81,
      "sgd": 1.84,
      "sol": 0.00975803,
      "thb": 46.93,
      "try": 56.52,
      "twd": 42.26,
      "uah": 59.58,
      "usd": 1.43,
      "vef": 0.143148,
      "vnd": 37356,
      "xag": 0.03889716,
      "xau": 0.00042375,
      "xdr": 1.014,
      "xlm": 5.677115,
      "xrp": 0.65963116,
      "yfi": 0.00028364,
      "zar": 25.78,
      "bits": 13.61,
      "link": 0.10825111,
      "sats": 1361.0
    },
    "total_value_locked": null,
    "mcap_to_tvl_ratio": null,
    "fdv_to_tvl_ratio": null,
    "roi": null,
    "ath": {
      "aed": 14.3,
      "ars": 3925.22,
      "aud": 6.07,
      "bch": 0.0104189,
      "bdt": 465.35,
      "bhd": 1.47,
      "bmd": 3.89,
      "bnb": 0.0065218,
      "brl": 23.37,
      "btc": 5.116e-05,
      "cad": 5.5,
      "chf": 3.45,
      "clp": 3801.42,
      "cny": 28.12,
      "czk": 91.99,
      "dkk": 27.41,
      "dot": 0.90285149,
      "eos": 8.325176,
      "eth": 0.00133352,
      "eur": 3.67,
      "gbp": 3.06,
      "gel": 10.86,
      "hkd": 30.26,
      "huf": 1505.91,
      "idr": 61952,
      "ils": 14.53,
      "inr": 328.41,
      "jpy": 594.41,
      "krw": 5545.58,
      "kwd": 1.19,
      "lkr": 1139.32,
      "ltc": 0.05443929,
      "mmk": 8165.94,
      "mxn": 78.17,
      "myr": 17.2,
      "ngn": 6532.99,
      "nok": 43.05,
      "nzd": 6.7,
      "php": 227.12,
      "pkr": 1081.38,
      "pln": 15.66,
      "rub": 412.71,
      "sar": 14.62,
      "sek": 42.4,
      "sgd": 5.21,
      "sol": 0.01007914,
      "thb": 132.64,
      "try": 135.08,
      "twd": 125.54,
      "uah": 160.76,
      "usd": 3.89,
      "vef": 0.389731,
      "vnd": 98413,
      "xag": 0.126483,
      "xau": 0.00145989,
      "xdr": 2.93,
      "xlm": 38.405853,
      "xrp": 7.065865,
      "yfi": 0.00075262,
      "zar": 69.1,
      "bits": 51.16,
      "link": 0.29717906,
      "sats": 5115.7
    },
    "ath_change_percentage": {
      "aed": -63.06967,
      "ars": -58.163,
      "aud": -63.51522,
      "bch": -69.88643,
      "bdt": -62.23445,
      "bhd": -63.04663,
      "bmd": -63.06358,
      "bnb": -65.82047,
      "brl": -66.24422,
      "btc": -73.23602,
      "cad": -64.1399,
      "chf": -65.79351,
      "clp": -64.32686,
      "cny": -63.23699,
      "czk": -66.1688,
      "dkk": -65.87266,
      "dot": -55.73814,
      "eos": -66.15982,
      "eth": -57.24451,
      "eur": -65.876,
      "gbp": -64.9536,
      "gel": -63.98782,
      "hkd": -62.7053,
      "huf": -66.40617,
      "idr": -62.01964,
      "ils": -65.67371,
      "inr": -62.13052,
      "jpy": -64.90752,
      "krw": -64.26196,
      "kwd": -63.0878,
      "lkr": -62.1056,
      "ltc": -68.95417,
      "mmk": -63.06358,
      "mxn": -64.96248,
      "myr": -64.39254,
      "ngn": -65.96399,
      "nok": -66.64222,
      "nzd": -64.23026,
      "php": -63.72948,
      "pkr": -62.32119,
      "pln": -65.78061,
      "rub": -72.65398,
      "sar": -63.10198,
      "sek": -67.2475,
      "sgd": -64.4899,
      "sol": -2.46668,
      "thb": -64.4591,
      "try": -57.92361,
      "twd": -66.15416,
      "uah": -62.73106,
      "usd": -63.06358,
      "vef": -63.06358,
      "vnd": -61.83203,
      "xag": -69.08785,
      "xau": -70.81624,
      "xdr": -65.16469,
      "xlm": -85.1168,
      "xrp": -90.5895,
      "yfi": -62.10085,
      "zar": -62.48977,
      "bits": -73.23602,
      "link": -63.26904,
      "sats": -73.23602
    },
    "ath_date": {
      "aed": "2024-11-08T12:26:05.892Z",
      "ars": "2024-12-16T01:02:07.531Z",
      "aud": "2024-12-16T01:02:07.531Z",
      "bch": "2024-11-08T12:26:05.892Z",
      "bdt": "2024-11-08T12:26:05.892Z",
      "bhd": "2024-11-08T12:26:05.892Z",
      "bmd": "2024-11-08T12:26:05.892Z",
      "bnb": "2024-11-08T12:26:05.892Z",
      "brl": "2024-12-16T01:02:07.531Z",
      "btc": "2024-11-08T12:26:05.892Z",
      "cad": "2024-12-16T01:02:07.531Z",
      "chf": "2024-12-16T01:02:07.531Z",
      "clp": "2024-12-16T01:02:07.531Z",
      "cny": "2024-12-16T01:02:07.531Z",
      "czk": "2024-12-16T01:02:07.531Z",
      "dkk": "2024-12-16T01:02:07.531Z",
      "dot": "2024-11-08T12:26:05.892Z",
      "eos": "2024-11-08T12:26:05.892Z",
      "eth": "2024-11-08T12:26:05.892Z",
      "eur": "2024-12-16T01:02:07.531Z",
      "gbp": "2024-12-16T01:02:07.531Z",
      "gel": "2024-12-16T01:02:07.531Z",
      "hkd": "2024-11-08T12:26:05.892Z",
      "huf": "2024-12-16T01:02:07.531Z",
      "idr": "2024-12-16T01:02:07.531Z",
      "ils": "2024-11-08T12:26:05.892Z",
      "inr": "2024-11-08T12:26:05.892Z",
      "jpy": "2024-12-16T01:02:07.531Z",
      "krw": "2024-12-16T01:02:07.531Z",
      "kwd": "2024-11-08T12:26:05.892Z",
      "lkr": "2024-11-08T12:26:05.892Z",
      "ltc": "2024-11-08T12:26:05.892Z",
      "mmk": "2024-11-08T12:26:05.892Z",
      "mxn": "2024-11-29T02:21:08.837Z",
      "myr": "2024-12-16T01:02:07.531Z",
      "ngn": "2024-11-08T12:26:05.892Z",
      "nok": "2024-12-16T01:02:07.531Z",
      "nzd": "2024-12-16T01:02:07.531Z",
      "php": "2024-11-08T12:26:05.892Z",
      "pkr": "2024-11-08T12:26:05.892Z",
      "pln": "2024-12-16T01:02:07.531Z",
      "rub": "2024-11-29T02:21:08.837Z",
      "sar": "2024-11-08T12:26:05.892Z",
      "sek": "2024-12-16T01:02:07.531Z",
      "sgd": "2024-12-16T01:02:07.531Z",
      "sol": "2025-06-17T05:12:02.425Z",
      "thb": "2024-11-08T12:26:05.892Z",
      "try": "2024-12-16T01:02:07.531Z",
      "twd": "2024-12-16T01:02:07.531Z",
      "uah": "2024-11-08T12:26:05.892Z",
      "usd": "2024-11-08T12:26:05.892Z",
      "vef": "2024-11-08T12:26:05.892Z",
      "vnd": "2024-11-08T12:26:05.892Z",
      "xag": "2024-12-16T01:02:07.531Z",
      "xau": "2024-12-16T01:02:07.531Z",
      "xdr": "2024-12-16T01:02:07.531Z",
      "xlm": "2024-11-08T12:26:05.892Z",
      "xrp": "2024-11-08T12:26:05.892Z",
      "yfi": "2024-11-08T12:26:05.892Z",
      "zar": "2024-11-29T02:21:08.837Z",
      "bits": "2024-11-08T12:26:05.892Z",
      "link": "2024-11-08T12:26:05.892Z",
      "sats": "2024-11-08T12:26:05.892Z"
    },
    "atl": {
      "aed": 2.41,
      "ars": 646.92,
      "aud": 0.992196,
      "bch": 0.0018102,
      "bdt": 78.22,
      "bhd": 0.246834,
      "bmd": 0.654959,
      "bnb": 0.00110471,
      "brl": 3.74,
      "btc": 9.47e-06,
      "cad": 0.910016,
      "chf": 0.566666,
      "clp": 620.22,
      "cny": 4.67,
      "czk": 15.36,
      "dkk": 4.51,
      "dot": 0.15907827,
      "eos": 1.454063,
      "eth": 0.00026023,
      "eur": 0.605297,
      "gbp": 0.504036,
      "gel": 1.78,
      "hkd": 5.09,
      "huf": 244.93,
      "idr": 10291.78,
      "ils": 2.44,
      "inr": 55.06,
      "jpy": 100.18,
      "krw": 906.27,
      "kwd": 0.200782,
      "lkr": 192.21,
      "ltc": 0.00933157,
      "mmk": 1374.1,
      "mxn": 13.1,
      "myr": 2.86,
      "ngn": 1075.96,
      "nok": 7.19,
      "nzd": 1.093,
      "php": 38.13,
      "pkr": 182.06,
      "pln": 2.63,
      "rub": 63.99,
      "sar": 2.46,
      "sek": 6.96,
      "sgd": 0.865787,
      "sol": 0.00941887,
      "thb": 22.12,
      "try": 22.46,
      "twd": 21.02,
      "uah": 27.09,
      "usd": 0.654959,
      "vef": 0.065581,
      "vnd": 16606.46,
      "xag": 0.01934805,
      "xau": 0.00023893,
      "xdr": 0.492065,
      "xlm": 3.410752,
      "xrp": 0.47099214,
      "yfi": 0.00013861,
      "zar": 11.59,
      "bits": 9.47,
      "link": 0.05838134,
      "sats": 947.0
    },
    "atl_change_percentage": {
      "aed": 119.46598,
      "ars": 153.84663,
      "aud": 123.255,
      "bch": 73.3234,
      "bdt": 124.66923,
      "bhd": 119.67253,
      "bmd": 119.50363,
      "bnb": 101.78389,
      "brl": 111.14968,
      "btc": 44.57928,
      "cad": 116.62378,
      "chf": 107.9839,
      "clp": 118.64597,
      "cny": 121.46884,
      "czk": 102.60124,
      "dkk": 107.19202,
      "dot": 151.20895,
      "eos": 93.75046,
      "eth": 119.09314,
      "eur": 107.1779,
      "gbp": 112.77364,
      "gel": 119.10159,
      "hkd": 121.71343,
      "huf": 106.54713,
      "idr": 128.6258,
      "ils": 104.34583,
      "inr": 125.86676,
      "jpy": 108.21141,
      "krw": 118.68618,
      "kwd": 119.39909,
      "lkr": 124.62169,
      "ltc": 81.1178,
      "mmk": 119.50363,
      "mxn": 109.11629,
      "myr": 114.44513,
      "ngn": 106.65908,
      "nok": 99.82651,
      "nzd": 119.23772,
      "php": 116.03505,
      "pkr": 123.80265,
      "pln": 103.60836,
      "rub": 76.37244,
      "sar": 119.31122,
      "sek": 99.5615,
      "sgd": 113.7001,
      "sol": 4.37043,
      "thb": 113.14313,
      "try": 153.1019,
      "twd": 102.09925,
      "uah": 121.19363,
      "usd": 119.50363,
      "vef": 119.50363,
      "vnd": 126.19154,
      "xag": 102.08072,
      "xau": 78.31661,
      "xdr": 107.24279,
      "xlm": 67.58827,
      "xrp": 41.17709,
      "yfi": 105.79143,
      "zar": 123.62009,
      "bits": 44.57928,
      "link": 86.97197,
      "sats": 44.57928
    },
    "atl_date": {
      "aed": "2024-10-28T15:20:48.857Z",
      "ars": "2024-10-28T15:20:48.857Z",
      "aud": "2024-10-28T15:20:48.857Z",
      "bch": "2024-10-28T15:20:48.857Z",
      "bdt": "2024-10-28T15:20:48.857Z",
      "bhd": "2024-10-28T15:20:48.857Z",
      "bmd": "2024-10-28T15:20:48.857Z",
      "bnb": "2024-10-28T20:16:19.590Z",
      "brl": "2024-10-28T15:20:48.857Z",
      "btc": "2024-10-28T20:16:19.590Z",
      "cad": "2024-10-28T15:20:48.857Z",
      "chf": "2024-10-28T15:20:48.857Z",
      "clp": "2024-10-28T15:20:48.857Z",
      "cny": "2024-10-28T15:20:48.857Z",
      "czk": "2024-10-28T15:20:48.857Z",
      "dkk": "2024-10-28T15:20:48.857Z",
      "dot": "2024-10-28T15:00:40.212Z",
      "eos": "2024-10-28T15:00:40.212Z",
      "eth": "2024-10-28T15:00:40.212Z",
      "eur": "2024-10-28T15:20:48.857Z",
      "gbp": "2024-10-28T15:20:48.857Z",
      "gel": "2024-10-28T15:20:48.857Z",
      "hkd": "2024-10-28T15:20:48.857Z",
      "huf": "2024-10-28T15:20:48.857Z",
      "idr": "2024-10-28T15:20:48.857Z",
      "ils": "2024-10-28T15:20:48.857Z",
      "inr": "2024-10-28T15:20:48.857Z",
      "jpy": "2024-10-28T15:20:48.857Z",
      "krw": "2024-10-28T15:20:48.857Z",
      "kwd": "2024-10-28T15:20:48.857Z",
      "lkr": "2024-10-28T15:20:48.857Z",
      "ltc": "2024-10-28T15:00:40.212Z",
      "mmk": "2024-10-28T15:20:48.857Z",
      "mxn": "2024-10-28T15:20:48.857Z",
      "myr": "2024-10-28T15:20:48.857Z",
      "ngn": "2024-10-28T15:20:48.857Z",
      "nok": "2024-10-28T15:20:48.857Z",
      "nzd": "2024-10-28T15:20:48.857Z",
      "php": "2024-10-28T15:20:48.857Z",
      "pkr": "2024-10-28T15:20:48.857Z",
      "pln": "2024-10-28T15:20:48.857Z",
      "rub": "2024-10-28T15:20:48.857Z",
      "sar": "2024-10-28T15:20:48.857Z",
      "sek": "2024-10-28T15:20:48.857Z",
      "sgd": "2024-10-28T15:20:48.857Z",
      "sol": "2025-06-18T13:26:26.733Z",
      "thb": "2024-10-28T15:20:48.857Z",
      "try": "2024-10-28T15:20:48.857Z",
      "twd": "2024-10-28T15:20:48.857Z",
      "uah": "2024-10-28T15:20:48.857Z",
      "usd": "2024-10-28T15:20:48.857Z",
      "vef": "2024-10-28T15:20:48.857Z",
      "vnd": "2024-10-28T15:20:48.857Z",
      "xag": "2024-10-28T15:00:40.212Z",
      "xau": "2024-10-28T15:20:48.857Z",
      "xdr": "2024-10-28T15:20:48.857Z",
      "xlm": "2025-02-03T03:50:30.860Z",
      "xrp": "2025-02-03T03:25:44.313Z",
      "yfi": "2024-10-28T20:16:19.590Z",
      "zar": "2024-10-28T15:20:48.857Z",
      "bits": "2024-10-28T20:16:19.590Z",
      "link": "2025-02-03T02:30:30.690Z",
      "sats": "2024-10-28T20:16:19.590Z"
    },
    "market_cap": {
      "aed": 1513383535,
      "ars": 470735563123,
      "aud": 634757570,
      "bch": 898083,
      "bdt": 50375506428,
      "bhd": 155403720,
      "bmd": 412099961,
      "bnb": 638801,
      "brl": 2260821598,
      "btc": 3920,
      "cad": 565039323,
      "chf": 337810701,
      "clp": 388717409529,
      "cny": 2962751462,
      "czk": 8918790993,
      "dkk": 2680826461,
      "dot": 114335778,
      "eos": 806623146,
      "eth": 163268,
      "eur": 359405151,
      "gbp": 307365992,
      "gel": 1120911895,
      "hkd": 3234883732,
      "huf": 144975242040,
      "idr": 6750356728189,
      "ils": 1429966261,
      "inr": 35665357642,
      "jpy": 59783098977,
      "krw": 568409661290,
      "kwd": 126274846,
      "lkr": 123755992085,
      "ltc": 4839924,
      "mmk": 864585718880,
      "mxn": 7849021116,
      "myr": 1755339785,
      "ngn": 637378526198,
      "nok": 4116261700,
      "nzd": 687301964,
      "php": 23614977833,
      "pkr": 116794715469,
      "pln": 1536752075,
      "rub": 32349296811,
      "sar": 1546312382,
      "sek": 3979834359,
      "sgd": 530387074,
      "sol": 2812922,
      "thb": 13527524510,
      "try": 16292825281,
      "twd": 12179820407,
      "uah": 17174542820,
      "usd": 412099961,
      "vef": 41263569,
      "vnd": 10768224754129,
      "xag": 11209960,
      "xau": 122151,
      "xdr": 292313629,
      "xlm": 1636995921,
      "xrp": 190317181,
      "yfi": 81770,
      "zar": 7432064968,
      "bits": 3920432877,
      "link": 31223755,
      "sats": 392043287688
    },
    "market_cap_rank": 174,
    "fully_diluted_valuation": {
      "aed": 5252911251,
      "ars": 1633909764954,
      "aud": 2203225492,
      "bch": 3117222,
      "bdt": 174851951532,
      "bhd": 539401895,
      "bmd": 1430387257,
      "bnb": 2217261,
      "brl": 7847247531,
      "btc": 13608,
      "cad": 1961235437,
      "chf": 1172531346,
      "clp": 1349227084146,
      "cny": 10283626146,
      "czk": 30956870135,
      "dkk": 9305072477,
      "dot": 396856237,
      "eos": 2799766020,
      "eth": 566700,
      "eur": 1247485069,
      "gbp": 1066858627,
      "gel": 3890653339,
      "hkd": 11228189523,
      "huf": 503204946050,
      "idr": 23430296410870,
      "ils": 4963372263,
      "inr": 123793443043,
      "jpy": 207505437979,
      "krw": 1972933784552,
      "kwd": 438296403,
      "lkr": 429553532342,
      "ltc": 16799239,
      "mmk": 3000952465426,
      "mxn": 27243729284,
      "myr": 6092734522,
      "ngn": 2212322755089,
      "nok": 14287427409,
      "nzd": 2385605589,
      "php": 81966917103,
      "pkr": 405391138996,
      "pln": 5334022791,
      "rub": 112283490116,
      "sar": 5367206345,
      "sek": 13813891986,
      "sgd": 1840958463,
      "sol": 9763573,
      "thb": 46953653227,
      "try": 56551933636,
      "twd": 42275810578,
      "uah": 59612350160,
      "usd": 1430387257,
      "vef": 143224676,
      "vnd": 37376202172326,
      "xag": 38909451,
      "xau": 423981,
      "xdr": 1014612302,
      "xlm": 5681966332,
      "xrp": 660585529,
      "yfi": 283820,
      "zar": 25796486344,
      "bits": 13607711127,
      "link": 108376765,
      "sats": 1360771112740
    },
    "market_cap_fdv_ratio": 0.29,
    "total_volume": {
      "aed": 140989853,
      "ars": 43853143450,
      "aud": 59159363,
      "bch": 83616,
      "bdt": 4693083457,
      "bhd": 14477723,
      "bmd": 38392061,
      "bnb": 59498,
      "brl": 210653399,
      "btc": 365.493,
      "cad": 52635477,
      "chf": 31468590,
      "clp": 36213695371,
      "cny": 276012043,
      "czk": 830884361,
      "dkk": 249741853,
      "dot": 10646688,
      "eos": 75127861,
      "eth": 15209,
      "eur": 33481332,
      "gbp": 28635103,
      "gel": 104426406,
      "hkd": 301371919,
      "huf": 13505386959,
      "idr": 628689107767,
      "ils": 133218532,
      "inr": 3323439466,
      "jpy": 5568909206,
      "krw": 52938854094,
      "kwd": 11764019,
      "lkr": 11529357029,
      "ltc": 450581,
      "mmk": 80546543783,
      "mxn": 731407152,
      "myr": 163530983,
      "ngn": 59379464922,
      "nok": 383478716,
      "nzd": 64019683,
      "php": 2200421736,
      "pkr": 10880830504,
      "pln": 143154397,
      "rub": 3013829724,
      "sar": 144057570,
      "sek": 370762767,
      "sgd": 49413846,
      "sol": 262049,
      "thb": 1260411360,
      "try": 1517872359,
      "twd": 1134765623,
      "uah": 1600014938,
      "usd": 38392061,
      "vef": 3844197,
      "vnd": 1003184551498,
      "xag": 1044572,
      "xau": 11379.79,
      "xdr": 27232525,
      "xlm": 152457322,
      "xrp": 17714210,
      "yfi": 7617,
      "zar": 692396979,
      "bits": 365493403,
      "link": 2907053,
      "sats": 36549340266
    },
    "high_24h": {
      "aed": 5.33,
      "ars": 1688.61,
      "aud": 2.23,
      "bch": 0.0031575,
      "bdt": 177.58,
      "bhd": 0.547731,
      "bmd": 1.45,
      "bnb": 0.00224221,
      "brl": 7.98,
      "btc": 1.377e-05,
      "cad": 1.98,
      "chf": 1.19,
      "clp": 1370.36,
      "cny": 10.44,
      "czk": 31.34,
      "dkk": 9.42,
      "dot": 0.40066914,
      "eos": 2.853393,
      "eth": 0.00057192,
      "eur": 1.26,
      "gbp": 1.081,
      "gel": 3.95,
      "hkd": 11.4,
      "huf": 510.07,
      "idr": 23714,
      "ils": 5.1,
      "inr": 125.4,
      "jpy": 210.55,
      "krw": 1992.65,
      "kwd": 0.444912,
      "lkr": 436.7,
      "ltc": 0.01699133,
      "mmk": 3047.51,
      "mxn": 27.58,
      "myr": 6.17,
      "ngn": 2242.06,
      "nok": 14.44,
      "nzd": 2.41,
      "php": 82.71,
      "pkr": 411.45,
      "pln": 5.4,
      "rub": 114.02,
      "sar": 5.45,
      "sek": 13.96,
      "sgd": 1.86,
      "sol": 0.00986896,
      "thb": 47.35,
      "try": 57.42,
      "twd": 42.9,
      "uah": 60.33,
      "usd": 1.45,
      "vef": 0.145447,
      "vnd": 37892,
      "xag": 0.03935486,
      "xau": 0.00042894,
      "xdr": 1.027,
      "xlm": 5.726562,
      "xrp": 0.66905662,
      "yfi": 0.00028681,
      "zar": 26.1,
      "bits": 13.77,
      "link": 0.11030408,
      "sats": 1377.18
    },
    "low_24h": {
      "aed": 4.99,
      "ars": 1572.48,
      "aud": 2.09,
      "bch": 0.00293944,
      "bdt": 166.21,
      "bhd": 0.512881,
      "bmd": 1.36,
      "bnb": 0.00212971,
      "brl": 7.45,
      "btc": 1.307e-05,
      "cad": 1.86,
      "chf": 1.11,
      "clp": 1283.83,
      "cny": 9.77,
      "czk": 29.34,
      "dkk": 8.82,
      "dot": 0.37630876,
      "eos": 2.732506,
      "eth": 0.00054932,
      "eur": 1.18,
      "gbp": 1.011,
      "gel": 3.7,
      "hkd": 10.67,
      "huf": 477.28,
      "idr": 22251,
      "ils": 4.76,
      "inr": 117.51,
      "jpy": 196.96,
      "krw": 1869.62,
      "kwd": 0.416481,
      "lkr": 408.33,
      "ltc": 0.01626804,
      "mmk": 2852.69,
      "mxn": 25.8,
      "myr": 5.78,
      "ngn": 2103.34,
      "nok": 13.53,
      "nzd": 2.26,
      "php": 77.81,
      "pkr": 385.24,
      "pln": 5.05,
      "rub": 106.84,
      "sar": 5.1,
      "sek": 13.05,
      "sgd": 1.75,
      "sol": 0.00941887,
      "thb": 44.38,
      "try": 53.76,
      "twd": 40.15,
      "uah": 56.67,
      "usd": 1.36,
      "vef": 0.136149,
      "vnd": 35488,
      "xag": 0.03668038,
      "xau": 0.00040097,
      "xdr": 0.964486,
      "xlm": 5.519068,
      "xrp": 0.64117615,
      "yfi": 0.00027504,
      "zar": 24.54,
      "bits": 13.07,
      "link": 0.10715793,
      "sats": 1307.14
    },
    "price_change_24h": -0.010388689910181,
    "price_change_percentage_24h": -0.72143,
    "price_change_percentage_7d": -19.80691,
    "price_change_percentage_14d": -27.23242,
    "price_change_percentage_30d": -30.79129,
    "price_change_percentage_60d": -16.34079,
    "price_change_percentage_200d": -56.50904,
    "price_change_percentage_1y": 0.0,
    "market_cap_change_24h": -2772142.3770903,
    "market_cap_change_percentage_24h": -0.66819,
    "price_change_24h_in_currency": {
      "aed": -0.038225993648249634,
      "ars": -40.99018592241396,
      "aud": -0.015351568543474414,
      "bch": 8.669e-05,
      "bdt": -1.2852540574895102,
      "bhd": -0.003891675575387499,
      "bmd": -0.010388689910180604,
      "bnb": 6.43e-06,
      "brl": -0.06664976487460983,
      "btc": -8.9436710323e-08,
      "cad": -0.007836282171238995,
      "chf": -0.004068486455871323,
      "clp": -9.995402349473807,
      "cny": -0.07022337958918357,
      "czk": -0.155634735081442,
      "dkk": -0.04088970094492517,
      "dot": 0.01261456,
      "eos": -0.03896988334882279,
      "eth": -3.354686139425e-06,
      "eur": -0.005612490356575073,
      "gbp": -0.005369612918343369,
      "gel": -0.02825723655569412,
      "hkd": -0.08154965749143805,
      "huf": -3.156943365001325,
      "idr": -86.61148283163857,
      "ils": -0.09753951102237401,
      "inr": -0.5035863816066382,
      "jpy": -1.5563578773387405,
      "krw": -5.338940477400001,
      "kwd": -0.003230801891287771,
      "lkr": -3.5932887118339636,
      "ltc": -0.000115569289789973,
      "mmk": -21.7954714315606,
      "mxn": -0.10846443474164502,
      "myr": -0.027690517900177625,
      "ngn": -11.877344118461679,
      "nok": -0.014645150660602013,
      "nzd": -0.005882515988095083,
      "php": 0.08786,
      "pkr": -2.7148372701803964,
      "pln": -0.025304420896376634,
      "rub": -0.8136026315484912,
      "sar": -0.03843689792316951,
      "sek": 0.066425,
      "sgd": -0.010305347186253755,
      "sol": 5.132e-05,
      "thb": 0.00958157,
      "try": -0.39877620609622255,
      "twd": -0.29482297498418575,
      "uah": -0.22962200220116813,
      "usd": -0.010388689910180604,
      "vef": -0.001040219520706431,
      "vnd": -207.8408877479378,
      "xag": 0.00023608,
      "xau": -1.063298577917e-06,
      "xdr": -0.00439247905676976,
      "xlm": -0.020000801466219187,
      "xrp": -0.004929110714614771,
      "yfi": -5.98871070442e-07,
      "zar": -0.13277111170268796,
      "bits": -0.08943671032348277,
      "link": -0.00188625263847976,
      "sats": -8.94367103234822
    },
    "price_change_percentage_1h_in_currency": {
      "aed": 0.24903,
      "ars": 0.24859,
      "aud": 0.16257,
      "bch": 0.24881,
      "bdt": 0.24903,
      "bhd": 0.2461,
      "bmd": 0.24903,
      "bnb": -0.04087,
      "brl": 0.25451,
      "btc": 0.11302,
      "cad": 0.21423,
      "chf": 0.19121,
      "clp": 0.24903,
      "cny": 0.24066,
      "czk": 0.16242,
      "dkk": 0.16758,
      "dot": 0.04251,
      "eos": 0.2739,
      "eth": 0.01096,
      "eur": 0.16713,
      "gbp": 0.18334,
      "gel": 0.24903,
      "hkd": 0.24935,
      "huf": 0.165,
      "idr": 0.38546,
      "ils": 0.24903,
      "inr": 0.22129,
      "jpy": 0.153,
      "krw": 0.16581,
      "kwd": 0.24772,
      "lkr": 0.24903,
      "ltc": 0.08111,
      "mmk": 0.24903,
      "mxn": 0.21957,
      "myr": 0.16789,
      "ngn": 0.24903,
      "nok": 0.25036,
      "nzd": 0.22703,
      "php": 0.30414,
      "pkr": 0.24903,
      "pln": 0.18806,
      "rub": 0.24631,
      "sar": 0.24814,
      "sek": 0.16821,
      "sgd": 0.23252,
      "sol": -0.28612,
      "thb": 0.40586,
      "try": 0.25181,
      "twd": 0.25682,
      "uah": 0.24903,
      "usd": 0.24903,
      "vef": 0.24903,
      "vnd": 0.27205,
      "xag": 0.14085,
      "xau": 0.34043,
      "xdr": 0.24903,
      "xlm": -0.07094,
      "xrp": -0.03487,
      "yfi": 0.01579,
      "zar": 0.21114,
      "bits": 0.11302,
      "link": -0.38604,
      "sats": 0.11302
    },
    "price_change_percentage_24h_in_currency": {
      "aed": -0.72284,
      "ars": -2.44868,
      "aud": -0.69204,
      "bch": 2.86389,
      "bdt": -0.73008,
      "bhd": -0.71669,
      "bmd": -0.72143,
      "bnb": 0.29106,
      "brl": -0.84251,
      "btc": -0.65285,
      "cad": -0.39822,
      "chf": -0.346,
      "clp": -0.73577,
      "cny": -0.67861,
      "czk": -0.5005,
      "dkk": -0.43776,
      "dot": 3.28641,
      "eos": -1.37385,
      "eth": -0.58883,
      "eur": -0.44815,
      "gbp": -0.50105,
      "gel": -0.72143,
      "hkd": -0.72143,
      "huf": -0.62382,
      "idr": -0.3686,
      "ils": -1.92832,
      "inr": -0.40527,
      "jpy": -0.74493,
      "krw": -0.2701,
      "kwd": -0.73212,
      "lkr": -0.83002,
      "ltc": -0.68408,
      "mmk": -0.72143,
      "mxn": -0.39666,
      "myr": -0.45267,
      "ngn": -0.53429,
      "nok": -0.10245,
      "nzd": -0.24615,
      "php": 0.10734,
      "pkr": -0.66558,
      "pln": -0.47245,
      "rub": -0.71974,
      "sar": -0.71143,
      "sek": 0.48345,
      "sgd": -0.55694,
      "sol": 0.52869,
      "thb": 0.02042,
      "try": -0.70059,
      "twd": -0.69288,
      "uah": -0.38392,
      "usd": -0.72143,
      "vef": -0.72143,
      "vnd": -0.5533,
      "xag": 0.61064,
      "xau": -0.2503,
      "xdr": -0.43129,
      "xlm": -0.35107,
      "xrp": -0.74171,
      "yfi": -0.2107,
      "zar": -0.51232,
      "bits": -0.65285,
      "link": -1.71264,
      "sats": -0.65285
    },
    "price_change_percentage_7d_in_currency": {
      "aed": -19.81193,
      "ars": -22.50409,
      "aud": -19.64624,
      "bch": -24.83342,
      "bdt": -19.80825,
      "bhd": -19.79393,
      "bmd": -19.80691,
      "bnb": -17.21804,
      "brl": -20.52677,
      "btc": -17.64294,
      "cad": -19.50489,
      "chf": -19.50207,
      "clp": -19.02138,
      "cny": -19.69409,
      "czk": -19.32759,
      "dkk": -19.44096,
      "dot": -7.87674,
      "eos": -3.95614,
      "eth": -12.07838,
      "eur": -19.43665,
      "gbp": -18.75355,
      "gel": -20.10065,
      "hkd": -19.78652,
      "huf": -18.80622,
      "idr": -19.07229,
      "ils": -20.13507,
      "inr": -18.74422,
      "jpy": -19.16221,
      "krw": -18.67741,
      "kwd": -19.64484,
      "lkr": -19.4613,
      "ltc": -14.83873,
      "mmk": -19.80691,
      "mxn": -19.20445,
      "myr": -19.16164,
      "ngn": -19.08864,
      "nok": -20.23053,
      "nzd": -19.24417,
      "php": -17.50467,
      "pkr": -19.50484,
      "pln": -18.97158,
      "rub": -20.81286,
      "sar": -19.7722,
      "sek": -18.72105,
      "sgd": -19.44578,
      "sol": -12.42178,
      "thb": -18.87532,
      "try": -19.11665,
      "twd": -19.99827,
      "uah": -19.51262,
      "usd": -19.80691,
      "vef": -19.80691,
      "vnd": -19.493,
      "xag": -20.64456,
      "xau": -19.81502,
      "xdr": -19.67577,
      "xlm": -11.85801,
      "xrp": -16.88947,
      "yfi": -12.66417,
      "zar": -18.3031,
      "bits": -17.64294,
      "link": -10.87411,
      "sats": -17.64294
    },
    "price_change_percentage_14d_in_currency": {
      "aed": -27.24448,
      "ars": -29.8739,
      "aud": -27.15787,
      "bch": -36.31737,
      "bdt": -27.1761,
      "bhd": -27.21871,
      "bmd": -27.23242,
      "bnb": -24.87669,
      "brl": -29.11597,
      "btc": -27.22552,
      "cad": -27.05903,
      "chf": -27.1276,
      "clp": -26.83606,
      "cny": -27.16555,
      "czk": -27.53415,
      "dkk": -27.54425,
      "dot": -18.61025,
      "eos": -8.17274,
      "eth": -24.4261,
      "eur": -27.54249,
      "gbp": -26.47047,
      "gel": -27.89515,
      "hkd": -27.19065,
      "huf": -27.49112,
      "idr": -26.81881,
      "ils": -27.5346,
      "inr": -26.64146,
      "jpy": -26.13295,
      "krw": -26.10352,
      "kwd": -27.21864,
      "lkr": -26.95568,
      "ltc": -24.12905,
      "mmk": -27.23242,
      "mxn": -27.78788,
      "myr": -26.90637,
      "ngn": -28.58134,
      "nok": -28.08412,
      "nzd": -26.75478,
      "php": -24.96627,
      "pkr": -26.86798,
      "pln": -27.61939,
      "rub": -27.96776,
      "sar": -27.1972,
      "sek": -26.66081,
      "sgd": -27.1764,
      "sol": -23.43057,
      "thb": -26.59067,
      "try": -26.82747,
      "twd": -28.06645,
      "uah": -26.8098,
      "usd": -27.23242,
      "vef": -27.23242,
      "vnd": -27.15676,
      "xag": -31.62901,
      "xau": -27.29619,
      "xdr": -27.98975,
      "xlm": -22.61838,
      "xrp": -25.8137,
      "yfi": -24.74007,
      "zar": -26.423,
      "bits": -27.22552,
      "link": -23.40522,
      "sats": -27.22552
    },
    "price_change_percentage_30d_in_currency": {
      "aed": -30.80259,
      "ars": -30.55498,
      "aud": -31.23385,
      "bch": -40.42815,
      "bdt": -30.37532,
      "bhd": -30.77128,
      "bmd": -30.79129,
      "bnb": -30.21569,
      "brl": -32.74036,
      "btc": -30.30927,
      "cad": -32.02247,
      "chf": -32.00141,
      "clp": -30.63096,
      "cny": -31.1037,
      "czk": -32.28963,
      "dkk": -32.13997,
      "dot": -10.85392,
      "eos": 5.21916,
      "eth": -30.02096,
      "eur": -32.12911,
      "gbp": -30.99916,
      "gel": -31.29646,
      "hkd": -30.56604,
      "huf": -31.91954,
      "idr": -30.90304,
      "ils": -32.18283,
      "inr": -29.85924,
      "jpy": -30.67483,
      "krw": -31.60431,
      "kwd": -31.00519,
      "lkr": -30.70517,
      "ltc": -20.14586,
      "mmk": -30.79129,
      "mxn": -31.75416,
      "myr": -31.20315,
      "ngn": -33.45993,
      "nok": -32.89783,
      "nzd": -31.65239,
      "php": -28.78651,
      "pkr": -30.58774,
      "pln": -31.74704,
      "rub": -32.71614,
      "sar": -30.76152,
      "sek": -30.92592,
      "sgd": -31.20552,
      "sol": -20.21116,
      "thb": -31.52237,
      "try": -29.52659,
      "twd": -32.20354,
      "uah": -30.70166,
      "usd": -30.79129,
      "vef": -30.79129,
      "vnd": -30.34856,
      "xag": -39.38565,
      "xau": -34.11858,
      "xdr": -32.68981,
      "xlm": -21.19236,
      "xrp": -23.93554,
      "yfi": -23.49608,
      "zar": -31.02191,
      "bits": -30.30927,
      "link": -15.63229,
      "sats": -30.30927
    },
    "price_change_percentage_60d_in_currency": {
      "aed": -16.3548,
      "ars": -16.02651,
      "aud": -17.64227,
      "bch": -38.11844,
      "bdt": -15.78072,
      "bhd": -16.29418,
      "bmd": -16.34079,
      "bnb": -23.17319,
      "brl": -20.96596,
      "btc": -32.17144,
      "cad": -17.13481,
      "chf": -16.21997,
      "clp": -18.4503,
      "cny": -17.562,
      "czk": -17.84753,
      "dkk": -17.11101,
      "dot": -9.34575,
      "eos": 4.57327,
      "eth": -46.61048,
      "eur": -17.02875,
      "gbp": -17.22672,
      "gel": -17.28351,
      "hkd": -15.41072,
      "huf": -18.04638,
      "idr": -18.76616,
      "ils": -21.24597,
      "inr": -15.18243,
      "jpy": -14.77753,
      "krw": -18.66992,
      "kwd": -16.39045,
      "lkr": -15.77217,
      "ltc": -24.85117,
      "mmk": -16.34079,
      "mxn": -19.17628,
      "myr": -19.14999,
      "ngn": -19.29019,
      "nok": -20.2073,
      "nzd": -16.66533,
      "php": -15.42591,
      "pkr": -15.43949,
      "pln": -17.08531,
      "rub": -20.08008,
      "sar": -16.33484,
      "sek": -16.0208,
      "sgd": -17.85147,
      "sol": -19.09621,
      "thb": -17.66232,
      "try": -13.00509,
      "twd": -23.96949,
      "uah": -15.56076,
      "usd": -16.34079,
      "vef": -16.34079,
      "vnd": -15.55426,
      "xag": -25.99122,
      "xau": -17.68762,
      "xdr": -17.36308,
      "xlm": -18.26487,
      "xrp": -19.61533,
      "yfi": -23.61284,
      "zar": -19.83548,
      "bits": -32.17144,
      "link": -17.47308,
      "sats": -32.17144
    },
    "price_change_percentage_200d_in_currency": {
      "aed": -56.5165,
      "ars": -50.82142,
      "aud": -56.38575,
      "bch": -51.46679,
      "bdt": -55.42657,
      "bhd": -56.47984,
      "bmd": -56.50904,
      "bnb": -56.29384,
      "brl": -60.05448,
      "btc": -60.27286,
      "cad": -57.44795,
      "chf": -59.53067,
      "clp": -57.87515,
      "cny": -56.82373,
      "czk": -60.58826,
      "dkk": -59.8794,
      "dot": 5.45381,
      "eos": -21.83614,
      "eth": -36.74302,
      "eur": -59.87972,
      "gbp": -58.68186,
      "gel": -57.93941,
      "hkd": -56.12731,
      "huf": -60.7998,
      "idr": -55.0274,
      "ils": -58.47113,
      "inr": -55.47813,
      "jpy": -57.87719,
      "krw": -57.02694,
      "kwd": -56.63514,
      "lkr": -54.97928,
      "ltc": -48.97564,
      "mmk": -56.50904,
      "mxn": -59.33615,
      "myr": -58.32402,
      "ngn": -59.9551,
      "nok": -60.66988,
      "nzd": -57.73197,
      "php": -57.46418,
      "pkr": -55.58669,
      "pln": -60.10388,
      "rub": -68.11146,
      "sar": -56.56327,
      "sek": -61.47634,
      "sgd": -58.20461,
      "sol": -29.04614,
      "thb": -58.29505,
      "try": -50.42332,
      "twd": -60.39085,
      "uah": -56.34127,
      "usd": -56.50904,
      "vef": -56.50904,
      "vnd": -55.16467,
      "xag": -63.77198,
      "xau": -65.84038,
      "xdr": -59.5962,
      "xlm": -13.99842,
      "xrp": -62.48255,
      "yfi": -32.19573,
      "zar": -56.57078,
      "bits": -60.27286,
      "link": -38.86116,
      "sats": -60.27286
    },
    "price_change_percentage_1y_in_currency": {},
    "market_cap_change_24h_in_currency": {
      "aed": -10201905.850748062,
      "ars": -11540728304.211426,
      "aud": -4340874.033166766,
      "bch": 26008,
      "bdt": -343286151.4683075,
      "bhd": -1037912.7368187308,
      "bmd": -2772142.3770902753,
      "bnb": 2342,
      "brl": -18319791.072793007,
      "btc": -26.433590547401764,
      "cad": -1904150.1421904564,
      "chf": -963901.6556653976,
      "clp": -2671367385.814209,
      "cny": -18602449.67397642,
      "czk": -39971320.00995064,
      "dkk": -10243514.415727615,
      "dot": 3749900,
      "eos": -10593637.485384226,
      "eth": -868.9025690675189,
      "eur": -1407457.7309360504,
      "gbp": -1385146.0977740884,
      "gel": -7540227.265685558,
      "hkd": -21800051.33512783,
      "huf": -823261367.6439819,
      "idr": -19321371441.82129,
      "ils": -27335064.01408291,
      "inr": -134369814.6817932,
      "jpy": -409864806.192543,
      "krw": -1069018297.1843262,
      "kwd": -863125.1023257226,
      "lkr": -968908983.3949127,
      "ltc": -27313.60928801354,
      "mmk": -5815954707.135498,
      "mxn": -28936306.80975914,
      "myr": -7036911.262530804,
      "ngn": -3080283907.149658,
      "nok": -2007724.6139264107,
      "nzd": -1211067.0920519829,
      "php": 33647458,
      "pkr": -719554933.463501,
      "pln": -6332354.31775713,
      "rub": -218181169.550457,
      "sar": -10245018.882793427,
      "sek": 21341309,
      "sgd": -2705325.1606814265,
      "sol": 16381,
      "thb": 8294702,
      "try": -106156259.77406883,
      "twd": -79152410.93122482,
      "uah": -56949710.784511566,
      "usd": -2772142.3770902753,
      "vef": -277574.6162180528,
      "vnd": -54055427543.552734,
      "xag": 71556,
      "xau": -240.8697767968988,
      "xdr": -1108814.7975421548,
      "xlm": -4364489.370842934,
      "xrp": -1145138.9308941662,
      "yfi": -119.56784729966603,
      "zar": -34384963.13813686,
      "bits": -26433590.54740429,
      "link": -507235.9918111339,
      "sats": -2643359054.7401733
    },
    "market_cap_change_percentage_24h_in_currency": {
      "aed": -0.6696,
      "ars": -2.39297,
      "aud": -0.67922,
      "bch": 2.98226,
      "bdt": -0.67684,
      "bhd": -0.66345,
      "bmd": -0.66819,
      "bnb": 0.36796,
      "brl": -0.8038,
      "btc": -0.66974,
      "cad": -0.33586,
      "chf": -0.28453,
      "clp": -0.68254,
      "cny": -0.62396,
      "czk": -0.44617,
      "dkk": -0.38065,
      "dot": 3.39094,
      "eos": -1.29631,
      "eth": -0.52938,
      "eur": -0.39008,
      "gbp": -0.44863,
      "gel": -0.66819,
      "hkd": -0.66939,
      "huf": -0.56466,
      "idr": -0.28541,
      "ils": -1.87573,
      "inr": -0.37534,
      "jpy": -0.68092,
      "krw": -0.18772,
      "kwd": -0.67889,
      "lkr": -0.77684,
      "ltc": -0.56117,
      "mmk": -0.66819,
      "mxn": -0.36731,
      "myr": -0.39929,
      "ngn": -0.48095,
      "nok": -0.04875,
      "nzd": -0.1759,
      "php": 0.14269,
      "pkr": -0.61231,
      "pln": -0.41037,
      "rub": -0.66994,
      "sar": -0.65818,
      "sek": 0.53913,
      "sgd": -0.50748,
      "sol": 0.58575,
      "thb": 0.06135,
      "try": -0.64733,
      "twd": -0.64567,
      "uah": -0.3305,
      "usd": -0.66819,
      "vef": -0.66819,
      "vnd": -0.49948,
      "xag": 0.64243,
      "xau": -0.1968,
      "xdr": -0.37789,
      "xlm": -0.26591,
      "xrp": -0.5981,
      "yfi": -0.14601,
      "zar": -0.46053,
      "bits": -0.66974,
      "link": -1.59855,
      "sats": -0.66974
    },
    "total_supply": 1000000000.0,
    "max_supply": 1000000000.0,
    "max_supply_infinite": false,
    "circulating_supply": 288103770.0,
    "last_updated": "2025-06-19T04:06:11.153Z"
  },
  "status_updates": [],
  "last_updated": "2025-06-19T04:06:11.153Z"
}