{
  "id": "ondo-finance",
  "symbol": "ondo",
  "name": "Ondo",
  "web_slug": "ondo",
  "asset_platform_id": "ethereum",
  "platforms": {
    "ethereum": "0xfaba6f8e4a5e8ab82f62fe7c39859fa577269be3"
  },
  "detail_platforms": {
    "ethereum": {
      "decimal_place": 18,
      "contract_address": "0xfaba6f8e4a5e8ab82f62fe7c39859fa577269be3"
    }
  },
  "block_time_in_minutes": 0,
  "hashing_algorithm": null,
  "categories": [
    "Decentralized Finance (DeFi)",
    "Ethereum Ecosystem",
    "Real World Assets (RWA)",
    "Coinbase Ventures Portfolio",
    "Pantera Capital Portfolio",
    "GMCI DeFi Index",
    "RWA Protocol",
    "GMCI Index",
    "World Liberty Financial Portfolio",
    "Binance Alpha Spotlight",
    "Made in USA"
  ],
  "preview_listing": false,
  "public_notice": null,
  "additional_notices": [],
  "description": {
    "en": "ONDO is a DeFi primitive that enables users to originate risk-isolated, fixed yield loans backed by yield-generating crypto-assets. It's unique because it's a permissionless protocol that allows users to interact on a peer-to-pool basis with no intermediaries."
  },
  "links": {
    "homepage": [
      "https://ondo.finance/",
      "https://docs.ondo.finance/",
      "https://fluxfinance.com/"
    ],
    "whitepaper": "",
    "blockchain_site": [
      "https://etherscan.io/address/0xfaba6f8e4a5e8ab82f62fe7c39859fa577269be3",
      "https://platform.arkhamintelligence.com/explorer/token/ondo-finance",
      "https://etherscan.io/token/0xfaba6f8e4a5e8ab82f62fe7c39859fa577269be3",
      "https://ethplorer.io/address/0xfaba6f8e4a5e8ab82f62fe7c39859fa577269be3"
    ],
    "official_forum_url": [
      "https://discord.com/invite/YzhZaFbB92"
    ],
    "chat_url": [
      "https://blog.ondo.finance/"
    ],
    "announcement_url": [],
    "snapshot_url": null,
    "twitter_screen_name": "OndoFinance",
    "facebook_username": "",
    "bitcointalk_thread_identifier": null,
    "telegram_channel_identifier": "ondofinance",
    "subreddit_url": "https://www.reddit.com",
    "repos_url": {
      "github": [
        "https://github.com/ondoprotocol/ondo-protocol"
      ],
      "bitbucket": []
    }
  },
  "image": {
    "thumb": "https://coin-images.coingecko.com/coins/images/26580/thumb/ONDO.png?1696525656",
    "small": "https://coin-images.coingecko.com/coins/images/26580/small/ONDO.png?1696525656",
    "large": "https://coin-images.coingecko.com/coins/images/26580/large/ONDO.png?1696525656"
  },
  "country_origin": "",
  "genesis_date": null,
  "contract_address": "0xfaba6f8e4a5e8ab82f62fe7c39859fa577269be3",
  "sentiment_votes_up_percentage": 80.95,
  "sentiment_votes_down_percentage": 19.05,
  "watchlist_portfolio_users": 183239,
  "market_cap_rank": 51,
  "market_data": {
    "current_price": {
      "aed": 2.83,
      "ars": 879.58,
      "aud": 1.19,
      "bch": 0.00167661,
      "bdt": 94.13,
      "bhd": 0.290395,
      "bmd": 0.770048,
      "bnb": 0.00119817,
      "brl": 4.22,
      "btc": 7.36e-06,
      "cad": 1.056,
      "chf": 0.631504,
      "clp": 726.36,
      "cny": 5.54,
      "czk": 16.69,
      "dkk": 5.01,
      "dot": 0.21402051,
      "eos": 1.510775,
      "eth": 0.00030622,
      "eur": 0.672335,
      "gbp": 0.57492,
      "gel": 2.09,
      "hkd": 6.04,
      "huf": 271.26,
      "idr": 12602.05,
      "ils": 2.67,
      "inr": 66.67,
      "jpy": 111.77,
      "krw": 1065.93,
      "kwd": 0.23596,
      "lkr": 231.25,
      "ltc": 0.00909552,
      "mmk": 1615.56,
      "mxn": 14.68,
      "myr": 3.28,
      "ngn": 1191.0,
      "nok": 7.7,
      "nzd": 1.29,
      "php": 44.11,
      "pkr": 218.24,
      "pln": 2.87,
      "rub": 60.45,
      "sar": 2.89,
      "sek": 7.45,
      "sgd": 0.991884,
      "sol": 0.00529273,
      "thb": 25.25,
      "try": 30.44,
      "twd": 22.78,
      "uah": 32.09,
      "usd": 0.770048,
      "vef": 0.077105,
      "vnd": 20123,
      "xag": 0.02101115,
      "xau": 0.00022808,
      "xdr": 0.546216,
      "xlm": 3.073844,
      "xrp": 0.35642288,
      "yfi": 0.00015337,
      "zar": 13.89,
      "bits": 7.36,
      "link": 0.05875384,
      "sats": 735.78
    },
    "total_value_locked": {
      "btc": 13344,
      "usd": 1396680047
    },
    "mcap_to_tvl_ratio": 1.74,
    "fdv_to_tvl_ratio": 5.51,
    "roi": null,
    "ath": {
      "aed": 7.86,
      "ars": 2174.32,
      "aud": 3.36,
      "bch": 0.0044714,
      "bdt": 255.31,
      "bhd": 0.806161,
      "bmd": 2.14,
      "bnb": 0.00294314,
      "brl": 12.94,
      "btc": 2.14e-05,
      "cad": 3.04,
      "chf": 1.91,
      "clp": 2105.34,
      "cny": 15.57,
      "czk": 50.95,
      "dkk": 15.18,
      "dot": 0.3094602,
      "eos": 2.439416,
      "eth": 0.00058707,
      "eur": 2.04,
      "gbp": 1.69,
      "gel": 6.01,
      "hkd": 16.64,
      "huf": 833.28,
      "idr": 34311,
      "ils": 7.7,
      "inr": 181.52,
      "jpy": 328.72,
      "krw": 3070.24,
      "kwd": 0.658381,
      "lkr": 619.98,
      "ltc": 0.01867617,
      "mmk": 4490.05,
      "mxn": 43.05,
      "myr": 9.53,
      "ngn": 3313.2,
      "nok": 23.84,
      "nzd": 3.71,
      "php": 125.57,
      "pkr": 594.02,
      "pln": 8.68,
      "rub": 220.87,
      "sar": 8.04,
      "sek": 23.48,
      "sgd": 2.89,
      "sol": 0.00532538,
      "thb": 72.94,
      "try": 74.82,
      "twd": 69.58,
      "uah": 89.01,
      "usd": 2.14,
      "vef": 0.214294,
      "vnd": 54374,
      "xag": 0.069965,
      "xau": 0.0008075,
      "xdr": 1.62,
      "xlm": 13.926134,
      "xrp": 2.835746,
      "yfi": 0.00025,
      "zar": 38.19,
      "bits": 21.4,
      "link": 0.09003879,
      "sats": 2139.92
    },
    "ath_change_percentage": {
      "aed": -64.03192,
      "ars": -59.55352,
      "aud": -64.68342,
      "bch": -62.49158,
      "bdt": -63.13759,
      "bhd": -63.98467,
      "bmd": -64.02574,
      "bnb": -59.28078,
      "brl": -67.35832,
      "btc": -65.61217,
      "cad": -65.31408,
      "chf": -66.91334,
      "clp": -65.50578,
      "cny": -64.44847,
      "czk": -67.25927,
      "dkk": -66.97691,
      "dot": -30.80884,
      "eos": -38.05567,
      "eth": -47.81573,
      "eur": -66.9823,
      "gbp": -66.08242,
      "gel": -65.17794,
      "hkd": -63.6828,
      "huf": -67.45801,
      "idr": -63.2805,
      "ils": -65.29067,
      "inr": -63.26625,
      "jpy": -66.00858,
      "krw": -65.28503,
      "kwd": -64.16724,
      "lkr": -62.70725,
      "ltc": -51.29089,
      "mmk": -64.02574,
      "mxn": -65.9099,
      "myr": -65.60565,
      "ngn": -64.05943,
      "nok": -67.73021,
      "nzd": -65.40756,
      "php": -64.87128,
      "pkr": -63.26669,
      "pln": -66.88275,
      "rub": -72.63541,
      "sar": -64.07545,
      "sek": -68.29734,
      "sgd": -65.63367,
      "sol": -0.58891,
      "thb": -65.38953,
      "try": -59.31958,
      "twd": -67.24885,
      "uah": -63.95354,
      "usd": -64.02574,
      "vef": -64.02574,
      "vnd": -62.99706,
      "xag": -69.99447,
      "xau": -71.75719,
      "xdr": -66.31591,
      "xlm": -77.92006,
      "xrp": -87.4246,
      "yfi": -38.60351,
      "zar": -63.63042,
      "bits": -65.61217,
      "link": -34.71848,
      "sats": -65.61217
    },
    "ath_date": {
      "aed": "2024-12-16T00:36:00.777Z",
      "ars": "2024-12-16T00:36:00.777Z",
      "aud": "2024-12-16T00:36:00.777Z",
      "bch": "2025-02-07T22:32:21.375Z",
      "bdt": "2024-12-16T00:36:00.777Z",
      "bhd": "2024-12-16T00:36:00.777Z",
      "bmd": "2024-12-16T00:36:00.777Z",
      "bnb": "2024-12-16T00:45:46.915Z",
      "brl": "2024-12-16T00:36:00.777Z",
      "btc": "2024-06-02T00:54:55.897Z",
      "cad": "2024-12-16T00:36:00.777Z",
      "chf": "2024-12-16T00:36:00.777Z",
      "clp": "2024-12-16T00:36:00.777Z",
      "cny": "2024-12-16T00:36:00.777Z",
      "czk": "2024-12-16T00:36:00.777Z",
      "dkk": "2024-12-16T00:36:00.777Z",
      "dot": "2025-02-07T22:35:27.328Z",
      "eos": "2025-02-07T22:32:21.375Z",
      "eth": "2025-04-11T13:26:28.726Z",
      "eur": "2024-12-16T00:36:00.777Z",
      "gbp": "2024-12-16T00:36:00.777Z",
      "gel": "2024-12-16T00:36:00.777Z",
      "hkd": "2024-12-16T00:36:00.777Z",
      "huf": "2024-12-16T00:36:00.777Z",
      "idr": "2024-12-16T00:36:00.777Z",
      "ils": "2024-12-16T00:36:00.777Z",
      "inr": "2024-12-16T00:36:00.777Z",
      "jpy": "2024-12-16T00:36:00.777Z",
      "krw": "2024-12-16T00:36:00.777Z",
      "kwd": "2024-12-16T00:36:00.777Z",
      "lkr": "2024-12-16T00:36:00.777Z",
      "ltc": "2024-12-21T04:35:47.395Z",
      "mmk": "2024-12-16T00:36:00.777Z",
      "mxn": "2024-12-16T00:36:00.777Z",
      "myr": "2024-12-16T00:36:00.777Z",
      "ngn": "2024-12-16T00:36:00.777Z",
      "nok": "2024-12-16T00:36:00.777Z",
      "nzd": "2024-12-16T00:36:00.777Z",
      "php": "2024-12-16T00:36:00.777Z",
      "pkr": "2024-12-16T00:36:00.777Z",
      "pln": "2024-12-16T00:36:00.777Z",
      "rub": "2024-12-16T00:36:00.777Z",
      "sar": "2024-12-16T00:36:00.777Z",
      "sek": "2024-12-16T00:36:00.777Z",
      "sgd": "2024-12-16T00:36:00.777Z",
      "sol": "2025-06-18T22:05:30.318Z",
      "thb": "2024-12-16T00:36:00.777Z",
      "try": "2024-12-16T00:36:00.777Z",
      "twd": "2024-12-16T00:36:00.777Z",
      "uah": "2024-12-16T00:36:00.777Z",
      "usd": "2024-12-16T00:36:00.777Z",
      "vef": "2024-12-16T00:36:00.777Z",
      "vnd": "2024-12-16T00:36:00.777Z",
      "xag": "2024-12-16T00:36:00.777Z",
      "xau": "2024-12-16T00:36:00.777Z",
      "xdr": "2024-12-16T00:36:00.777Z",
      "xlm": "2024-06-26T03:05:00.726Z",
      "xrp": "2024-06-03T08:29:55.744Z",
      "yfi": "2025-02-07T15:07:15.093Z",
      "zar": "2024-12-16T00:36:00.777Z",
      "bits": "2024-06-02T00:54:55.897Z",
      "link": "2024-06-26T02:20:09.216Z",
      "sats": "2024-06-02T00:54:55.897Z"
    },
    "atl": {
      "aed": 0.30181,
      "ars": 67.27,
      "aud": 0.125014,
      "bch": 0.00034184,
      "bdt": 9.0,
      "bhd": 0.03096836,
      "bmd": 0.082171,
      "bnb": 0.00026401,
      "brl": 0.403969,
      "btc": 1.94e-06,
      "cad": 0.110823,
      "chf": 0.071056,
      "clp": 75.52,
      "cny": 0.585103,
      "czk": 1.87,
      "dkk": 0.562616,
      "dot": 0.01144637,
      "eos": 0.11067212,
      "eth": 3.267e-05,
      "eur": 0.075442,
      "gbp": 0.064761,
      "gel": 0.219705,
      "hkd": 0.642691,
      "huf": 28.79,
      "idr": 1282.67,
      "ils": 0.309576,
      "inr": 6.83,
      "jpy": 12.14,
      "krw": 109.87,
      "kwd": 0.02528434,
      "lkr": 26.38,
      "ltc": 0.00119609,
      "mmk": 172.28,
      "mxn": 1.41,
      "myr": 0.387683,
      "ngn": 70.59,
      "nok": 0.862883,
      "nzd": 0.134157,
      "php": 4.59,
      "pkr": 22.97,
      "pln": 0.33175,
      "rub": 7.31,
      "sar": 0.308189,
      "sek": 0.857603,
      "sgd": 0.11038,
      "sol": 0.0049959,
      "thb": 2.92,
      "try": 2.48,
      "twd": 2.59,
      "uah": 3.11,
      "usd": 0.082171,
      "vef": 0.00822778,
      "vnd": 2018.2,
      "xag": 0.00363499,
      "xau": 4.079e-05,
      "xdr": 0.061398,
      "xlm": 0.70595245,
      "xrp": 0.14632349,
      "yfi": 1.062e-05,
      "zar": 1.55,
      "bits": 1.94,
      "link": 0.00532288,
      "sats": 193.81
    },
    "atl_change_percentage": {
      "aed": 836.80856,
      "ars": 1207.3406,
      "aud": 849.36229,
      "bch": 390.61895,
      "bdt": 945.31884,
      "bhd": 837.54196,
      "bmd": 836.95524,
      "bnb": 353.92407,
      "brl": 945.66508,
      "btc": 279.69237,
      "cad": 852.75872,
      "chf": 788.51547,
      "clp": 861.68923,
      "cny": 846.17142,
      "czk": 793.20508,
      "dkk": 791.11981,
      "dot": 1770.62859,
      "eos": 1265.36637,
      "eth": 837.82274,
      "eur": 790.93079,
      "gbp": 787.4765,
      "gel": 853.16251,
      "hkd": 840.3568,
      "huf": 841.84288,
      "idr": 882.2335,
      "ils": 762.96386,
      "inr": 876.01726,
      "jpy": 820.11992,
      "krw": 870.05716,
      "kwd": 833.05157,
      "lkr": 776.57752,
      "ltc": 660.56281,
      "mmk": 837.599,
      "mxn": 940.82636,
      "myr": 745.20592,
      "ngn": 1586.84445,
      "nok": 791.68231,
      "nzd": 856.78642,
      "php": 861.15962,
      "pkr": 849.92122,
      "pln": 766.11972,
      "rub": 726.73176,
      "sar": 837.38543,
      "sek": 767.89981,
      "sgd": 798.34336,
      "sol": 5.96733,
      "thb": 764.61045,
      "try": 1128.6974,
      "twd": 780.17085,
      "uah": 932.84479,
      "usd": 836.95524,
      "vef": 836.95524,
      "vnd": 896.92478,
      "xag": 477.5385,
      "xau": 459.16045,
      "xdr": 789.46539,
      "xlm": 335.56501,
      "xrp": 143.71102,
      "yfi": 1344.93282,
      "zar": 795.378,
      "bits": 279.69237,
      "link": 1004.26453,
      "sats": 279.69237
    },
    "atl_date": {
      "aed": "2024-01-18T12:14:30.524Z",
      "ars": "2024-01-18T12:14:30.524Z",
      "aud": "2024-01-18T12:14:30.524Z",
      "bch": "2024-01-18T12:14:30.524Z",
      "bdt": "2024-01-18T12:14:30.524Z",
      "bhd": "2024-01-18T12:14:30.524Z",
      "bmd": "2024-01-18T12:14:30.524Z",
      "bnb": "2024-01-18T12:14:30.524Z",
      "brl": "2024-01-18T12:14:30.524Z",
      "btc": "2024-01-18T12:14:30.524Z",
      "cad": "2024-01-18T12:14:30.524Z",
      "chf": "2024-01-18T12:14:30.524Z",
      "clp": "2024-01-18T12:14:30.524Z",
      "cny": "2024-01-18T12:14:30.524Z",
      "czk": "2024-01-18T12:14:30.524Z",
      "dkk": "2024-01-18T12:14:30.524Z",
      "dot": "2024-01-18T12:14:30.524Z",
      "eos": "2024-01-18T12:14:30.524Z",
      "eth": "2024-01-18T12:14:30.524Z",
      "eur": "2024-01-18T12:14:30.524Z",
      "gbp": "2024-01-18T12:14:30.524Z",
      "gel": "2024-01-18T12:14:30.524Z",
      "hkd": "2024-01-18T12:14:30.524Z",
      "huf": "2024-01-18T12:14:30.524Z",
      "idr": "2024-01-18T12:14:30.524Z",
      "ils": "2024-01-18T12:14:30.524Z",
      "inr": "2024-01-18T12:14:30.524Z",
      "jpy": "2024-01-18T12:14:30.524Z",
      "krw": "2024-01-18T12:14:30.524Z",
      "kwd": "2024-01-18T12:14:30.524Z",
      "lkr": "2024-01-18T12:14:30.524Z",
      "ltc": "2024-01-18T12:14:30.524Z",
      "mmk": "2024-01-18T12:14:30.524Z",
      "mxn": "2024-01-18T12:14:30.524Z",
      "myr": "2024-01-18T12:14:30.524Z",
      "ngn": "2024-01-18T12:14:30.524Z",
      "nok": "2024-01-18T12:14:30.524Z",
      "nzd": "2024-01-18T12:14:30.524Z",
      "php": "2024-01-18T12:14:30.524Z",
      "pkr": "2024-01-18T12:14:30.524Z",
      "pln": "2024-01-18T12:14:30.524Z",
      "rub": "2024-01-18T12:14:30.524Z",
      "sar": "2024-01-18T12:14:30.524Z",
      "sek": "2024-01-18T12:14:30.524Z",
      "sgd": "2024-01-18T12:14:30.524Z",
      "sol": "2025-06-17T17:20:17.921Z",
      "thb": "2024-01-18T12:14:30.524Z",
      "try": "2024-01-18T12:14:30.524Z",
      "twd": "2024-01-18T12:14:30.524Z",
      "uah": "2024-01-18T12:14:30.524Z",
      "usd": "2024-01-18T12:14:30.524Z",
      "vef": "2024-01-18T12:14:30.524Z",
      "vnd": "2024-01-18T12:14:30.524Z",
      "xag": "2024-01-18T12:14:30.524Z",
      "xau": "2024-01-18T12:14:30.524Z",
      "xdr": "2024-01-18T12:14:30.524Z",
      "xlm": "2024-01-18T12:14:30.524Z",
      "xrp": "2024-01-18T12:14:30.524Z",
      "yfi": "2024-01-18T12:14:30.524Z",
      "zar": "2024-01-18T12:14:30.524Z",
      "bits": "2024-01-18T12:14:30.524Z",
      "link": "2024-01-18T12:14:30.524Z",
      "sats": "2024-01-18T12:14:30.524Z"
    },
    "market_cap": {
      "aed": 8932164869,
      "ars": 2778282940510,
      "aud": 3749409230,
      "bch": 5300458,
      "bdt": 297322072269,
      "bhd": 917237503,
      "bmd": 2432261692,
      "bnb": 3787252,
      "brl": 13344846998,
      "btc": 23249,
      "cad": 3335676652,
      "chf": 1994522691,
      "clp": 2294255163320,
      "cny": 17489420920,
      "czk": 52702976014,
      "dkk": 15838759227,
      "dot": 676648293,
      "eos": 4782096733,
      "eth": 968126,
      "eur": 2123403373,
      "gbp": 1815683353,
      "gel": 6615751801,
      "hkd": 19092707021,
      "huf": 856659639864,
      "idr": 39801895162353,
      "ils": 8439826457,
      "inr": 210652104465,
      "jpy": 352996571579,
      "krw": 3367150694595,
      "kwd": 745298492,
      "lkr": 730422195847,
      "ltc": 28748906,
      "mmk": 5102885029202,
      "mxn": 46363769935,
      "myr": 10351705760,
      "ngn": 3761881868096,
      "nok": 24307196378,
      "nzd": 4055088583,
      "php": 139349141706,
      "pkr": 689335935169,
      "pln": 9077400079,
      "rub": 190936855199,
      "sar": 9126595004,
      "sek": 23514116105,
      "sgd": 3132594962,
      "sol": 16730031,
      "thb": 79749042561,
      "try": 96159881898,
      "twd": 71994948507,
      "uah": 101366140482,
      "usd": 2432261692,
      "vef": 243542363,
      "vnd": 63562294789388,
      "xag": 66321963,
      "xau": 720485,
      "xdr": 1725268889,
      "xlm": 9718497027,
      "xrp": 1126978949,
      "yfi": 484812,
      "zar": 43879946728,
      "bits": 23249113024,
      "link": 185711926,
      "sats": 2324911302413
    },
    "market_cap_rank": 51,
    "fully_diluted_valuation": {
      "aed": 28274329971,
      "ars": 8794518436001,
      "aud": 11868571094,
      "bch": 16778339,
      "bdt": 941158442818,
      "bhd": 2903470347,
      "bmd": 7699205137,
      "bnb": 11988361,
      "brl": 42242458907,
      "btc": 73594,
      "cad": 10558920902,
      "chf": 6313563790,
      "clp": 7262352237963,
      "cny": 55361904461,
      "czk": 166828686680,
      "dkk": 50136815797,
      "dot": 2141896998,
      "eos": 15137492756,
      "eth": 3064555,
      "eur": 6721529272,
      "gbp": 5747456635,
      "gel": 20941837974,
      "hkd": 60437028008,
      "huf": 2711714090135,
      "idr": 125990947750208,
      "ils": 26715856867,
      "inr": 666808908943,
      "jpy": 1117393340805,
      "krw": 10658550440861,
      "kwd": 2359205837,
      "lkr": 2312115650202,
      "ltc": 91003253,
      "mmk": 16152932378396,
      "mxn": 146762240631,
      "myr": 32767817065,
      "ngn": 11908052617908,
      "nok": 76943238414,
      "nzd": 12836184098,
      "php": 441102876134,
      "pkr": 2182059106382,
      "pln": 28734064908,
      "rub": 604401253982,
      "sar": 28889789031,
      "sek": 74432781692,
      "sgd": 9916075769,
      "sol": 52958094,
      "thb": 252441684332,
      "try": 304389391674,
      "twd": 227896479768,
      "uah": 320869547970,
      "usd": 7699205137,
      "vef": 770921410,
      "vnd": 201203327857308,
      "xag": 209938923,
      "xau": 2280659,
      "xdr": 5461254083,
      "xlm": 30763425865,
      "xrp": 3567396609,
      "yfi": 1534649,
      "zar": 138899820044,
      "bits": 73593927433,
      "link": 587861998,
      "sats": 7359392743269
    },
    "market_cap_fdv_ratio": 0.32,
    "total_volume": {
      "aed": 601551437,
      "ars": 187105106999,
      "aud": 252683316,
      "bch": 356649,
      "bdt": 20023647411,
      "bhd": 61772879,
      "bmd": 163804692,
      "bnb": 254875,
      "brl": 898730824,
      "btc": 1565,
      "cad": 224660756,
      "chf": 134333607,
      "clp": 154510413945,
      "cny": 1177821259,
      "czk": 3549960219,
      "dkk": 1066789197,
      "dot": 45526448,
      "eos": 321372208,
      "eth": 65140,
      "eur": 143019023,
      "gbp": 122297075,
      "gel": 445548763,
      "hkd": 1285828340,
      "huf": 57702204186,
      "idr": 2680707824764,
      "ils": 568394092,
      "inr": 14181623009,
      "jpy": 23775759656,
      "krw": 226744706848,
      "kwd": 50193361,
      "lkr": 49191492576,
      "ltc": 1934798,
      "mmk": 343662244192,
      "mxn": 3122546601,
      "myr": 697562282,
      "ngn": 253350165206,
      "nok": 1637708665,
      "nzd": 273403136,
      "php": 9382282469,
      "pkr": 46424470300,
      "pln": 611403634,
      "rub": 12858448838,
      "sar": 614645657,
      "sek": 1584473287,
      "sgd": 210993548,
      "sol": 1125870,
      "thb": 5371237759,
      "try": 6476001797,
      "twd": 4845097251,
      "uah": 6826670623,
      "usd": 163804692,
      "vef": 16401764,
      "vnd": 4280626118370,
      "xag": 4469493,
      "xau": 48517,
      "xdr": 116191091,
      "xlm": 653868111,
      "xrp": 75818285,
      "yfi": 32625,
      "zar": 2955694650,
      "bits": 1565144369,
      "link": 12498118,
      "sats": 156514436943
    },
    "high_24h": {
      "aed": 2.89,
      "ars": 897.36,
      "aud": 1.21,
      "bch": 0.00171277,
      "bdt": 96.03,
      "bhd": 0.296268,
      "bmd": 0.785597,
      "bnb": 0.00121768,
      "brl": 4.31,
      "btc": 7.47e-06,
      "cad": 1.076,
      "chf": 0.643006,
      "clp": 740.81,
      "cny": 5.65,
      "czk": 16.98,
      "dkk": 5.1,
      "dot": 0.21524092,
      "eos": 1.537784,
      "eth": 0.00031042,
      "eur": 0.684115,
      "gbp": 0.585202,
      "gel": 2.14,
      "hkd": 6.17,
      "huf": 275.84,
      "idr": 12838.91,
      "ils": 2.73,
      "inr": 68.04,
      "jpy": 114.0,
      "krw": 1079.83,
      "kwd": 0.240726,
      "lkr": 235.92,
      "ltc": 0.00921944,
      "mmk": 1648.18,
      "mxn": 14.94,
      "myr": 3.34,
      "ngn": 1215.04,
      "nok": 7.84,
      "nzd": 1.3,
      "php": 44.92,
      "pkr": 222.65,
      "pln": 2.92,
      "rub": 61.67,
      "sar": 2.95,
      "sek": 7.57,
      "sgd": 1.009,
      "sol": 0.00532538,
      "thb": 25.65,
      "try": 31.05,
      "twd": 23.22,
      "uah": 32.74,
      "usd": 0.785597,
      "vef": 0.078662,
      "vnd": 20504,
      "xag": 0.02138164,
      "xau": 0.00023317,
      "xdr": 0.557245,
      "xlm": 3.113181,
      "xrp": 0.36113343,
      "yfi": 0.00015559,
      "zar": 14.14,
      "bits": 7.47,
      "link": 0.05987577,
      "sats": 747.08
    },
    "low_24h": {
      "aed": 2.65,
      "ars": 840.84,
      "aud": 1.11,
      "bch": 0.00156355,
      "bdt": 88.35,
      "bhd": 0.272624,
      "bmd": 0.722764,
      "bnb": 0.00113273,
      "brl": 3.96,
      "btc": 6.95e-06,
      "cad": 0.986672,
      "chf": 0.59061,
      "clp": 682.43,
      "cny": 5.2,
      "czk": 15.59,
      "dkk": 4.69,
      "dot": 0.19997696,
      "eos": 1.460605,
      "eth": 0.00029227,
      "eur": 0.628425,
      "gbp": 0.537471,
      "gel": 1.97,
      "hkd": 5.67,
      "huf": 253.68,
      "idr": 11827.32,
      "ils": 2.53,
      "inr": 62.47,
      "jpy": 104.67,
      "krw": 993.87,
      "kwd": 0.221382,
      "lkr": 217.05,
      "ltc": 0.00865653,
      "mmk": 1516.36,
      "mxn": 13.71,
      "myr": 3.07,
      "ngn": 1117.49,
      "nok": 7.19,
      "nzd": 1.2,
      "php": 41.36,
      "pkr": 204.78,
      "pln": 2.69,
      "rub": 56.79,
      "sar": 2.71,
      "sek": 6.94,
      "sgd": 0.928624,
      "sol": 0.00501143,
      "thb": 23.58,
      "try": 28.58,
      "twd": 21.34,
      "uah": 30.12,
      "usd": 0.722764,
      "vef": 0.07237,
      "vnd": 18863.74,
      "xag": 0.01947348,
      "xau": 0.00021288,
      "xdr": 0.512676,
      "xlm": 2.935506,
      "xrp": 0.34093186,
      "yfi": 0.00014638,
      "zar": 13.03,
      "bits": 6.95,
      "link": 0.05703676,
      "sats": 695.45
    },
    "price_change_24h": 0.02049882,
    "price_change_percentage_24h": 2.73482,
    "price_change_percentage_7d": -10.42795,
    "price_change_percentage_14d": -6.99484,
    "price_change_percentage_30d": -18.13863,
    "price_change_percentage_60d": -10.26253,
    "price_change_percentage_200d": -38.28796,
    "price_change_percentage_1y": -34.833,
    "market_cap_change_24h": 70867373,
    "market_cap_change_percentage_24h": 3.00108,
    "price_change_24h_in_currency": {
      "aed": 0.07524,
      "ars": 8.25,
      "aud": 0.03298919,
      "bch": 0.00010314,
      "bdt": 2.5,
      "bhd": 0.00780008,
      "bmd": 0.02049882,
      "bnb": 4.781e-05,
      "brl": 0.106923,
      "btc": 2.2339e-07,
      "cad": 0.03172055,
      "chf": 0.01952188,
      "clp": 19.23,
      "cny": 0.150168,
      "czk": 0.502745,
      "dkk": 0.153282,
      "dot": 0.01362861,
      "eos": 0.03824155,
      "eth": 9.24e-06,
      "eur": 0.02047687,
      "gbp": 0.01705768,
      "gel": 0.055757,
      "hkd": 0.160896,
      "huf": 7.86,
      "idr": 375.06,
      "ils": 0.03912264,
      "inr": 1.92,
      "jpy": 2.95,
      "krw": 37.09,
      "kwd": 0.00625206,
      "lkr": 5.91,
      "ltc": 0.00028142,
      "mmk": 43.01,
      "mxn": 0.439872,
      "myr": 0.096289,
      "ngn": 34.19,
      "nok": 0.255533,
      "nzd": 0.04153803,
      "php": 1.52,
      "pkr": 5.93,
      "pln": 0.08637,
      "rub": 1.61,
      "sar": 0.077205,
      "sek": 0.293391,
      "sgd": 0.02836345,
      "sol": 0.00022424,
      "thb": 0.794343,
      "try": 0.814464,
      "twd": 0.626563,
      "uah": 0.960141,
      "usd": 0.02049882,
      "vef": 0.00205255,
      "vnd": 565.57,
      "xag": 0.00082399,
      "xau": 6e-06,
      "xdr": 0.01608969,
      "xlm": 0.10315697,
      "xrp": 0.0100599,
      "yfi": 4.56e-06,
      "zar": 0.407905,
      "bits": 0.22339,
      "link": 0.00134944,
      "sats": 22.34
    },
    "price_change_percentage_1h_in_currency": {
      "aed": -0.67353,
      "ars": -0.67309,
      "aud": -0.54729,
      "bch": -1.08704,
      "bdt": -0.67353,
      "bhd": -0.668,
      "bmd": -0.67353,
      "bnb": -0.62516,
      "brl": -0.68439,
      "btc": -0.55618,
      "cad": -0.59264,
      "chf": -0.60529,
      "clp": -0.67353,
      "cny": -0.65971,
      "czk": -0.54416,
      "dkk": -0.54809,
      "dot": -0.2948,
      "eos": -0.41668,
      "eth": -0.48488,
      "eur": -0.55165,
      "gbp": -0.57712,
      "gel": -0.67353,
      "hkd": -0.67263,
      "huf": -0.51626,
      "idr": -0.59261,
      "ils": -0.67353,
      "inr": -0.69404,
      "jpy": -0.56049,
      "krw": -0.50707,
      "kwd": -0.66996,
      "lkr": -0.67353,
      "ltc": -0.42904,
      "mmk": -0.67353,
      "mxn": -0.60741,
      "myr": -0.58014,
      "ngn": -0.67353,
      "nok": -0.56707,
      "nzd": -0.33945,
      "php": -0.57155,
      "pkr": -0.67353,
      "pln": -0.54963,
      "rub": -0.6779,
      "sar": -0.66913,
      "sek": -0.49288,
      "sgd": -0.55927,
      "sol": -0.27655,
      "thb": -0.58105,
      "try": -0.70317,
      "twd": -0.59959,
      "uah": -0.67353,
      "usd": -0.67353,
      "vef": -0.67353,
      "vnd": -0.58667,
      "xag": -0.58328,
      "xau": -0.56274,
      "xdr": -0.67353,
      "xlm": -0.38637,
      "xrp": -0.29041,
      "yfi": -0.45593,
      "zar": -0.57654,
      "bits": -0.55618,
      "link": -0.47225,
      "sats": -0.55618
    },
    "price_change_percentage_24h_in_currency": {
      "aed": 2.73336,
      "ars": 0.94655,
      "aud": 2.85651,
      "bch": 6.55523,
      "bdt": 2.72587,
      "bhd": 2.76016,
      "bmd": 2.73482,
      "bnb": 4.15587,
      "brl": 2.59646,
      "btc": 3.13118,
      "cad": 3.09646,
      "chf": 3.18994,
      "clp": 2.71998,
      "cny": 2.78771,
      "czk": 3.10611,
      "dkk": 3.15284,
      "dot": 6.80098,
      "eos": 2.59699,
      "eth": 3.11037,
      "eur": 3.14131,
      "gbp": 3.05768,
      "gel": 2.73482,
      "hkd": 2.73456,
      "huf": 2.98459,
      "idr": 3.06747,
      "ils": 1.48591,
      "inr": 2.96485,
      "jpy": 2.71343,
      "krw": 3.6047,
      "kwd": 2.72175,
      "lkr": 2.62245,
      "ltc": 3.19279,
      "mmk": 2.73482,
      "mxn": 3.08915,
      "myr": 3.02513,
      "ngn": 2.95582,
      "nok": 3.43303,
      "nzd": 3.33978,
      "php": 3.56794,
      "pkr": 2.79261,
      "pln": 3.0981,
      "rub": 2.733,
      "sar": 2.74531,
      "sek": 4.10036,
      "sgd": 2.94373,
      "sol": 4.42415,
      "thb": 3.24806,
      "try": 2.74884,
      "twd": 2.82869,
      "uah": 3.08408,
      "usd": 2.73482,
      "vef": 2.73482,
      "vnd": 2.8918,
      "xag": 4.08173,
      "xau": 2.70015,
      "xdr": 3.03507,
      "xlm": 3.4725,
      "xrp": 2.90444,
      "yfi": 3.06731,
      "zar": 3.02446,
      "bits": 3.13118,
      "link": 2.35076,
      "sats": 3.13118
    },
    "price_change_percentage_7d_in_currency": {
      "aed": -10.43356,
      "ars": -13.44134,
      "aud": -10.28978,
      "bch": -16.738,
      "bdt": -10.42946,
      "bhd": -10.41085,
      "bmd": -10.42795,
      "bnb": -6.79254,
      "brl": -11.24327,
      "btc": -7.1319,
      "cad": -10.10837,
      "chf": -10.07047,
      "clp": -9.55056,
      "cny": -10.38059,
      "czk": -9.77597,
      "dkk": -9.92306,
      "dot": 4.16219,
      "eos": 9.16822,
      "eth": -1.21507,
      "eur": -9.91651,
      "gbp": -9.16323,
      "gel": -10.75606,
      "hkd": -10.4178,
      "huf": -9.21499,
      "idr": -9.78939,
      "ils": -10.7945,
      "inr": -9.24241,
      "jpy": -9.7041,
      "krw": -9.46876,
      "kwd": -10.24253,
      "lkr": -10.04193,
      "ltc": -3.18039,
      "mmk": -10.42795,
      "mxn": -9.75211,
      "myr": -9.81379,
      "ngn": -9.6846,
      "nok": -10.91602,
      "nzd": -9.97342,
      "php": -8.15209,
      "pkr": -10.09055,
      "pln": -9.43057,
      "rub": -11.55466,
      "sar": -10.39137,
      "sek": -9.134,
      "sgd": -10.08171,
      "sol": -1.29207,
      "thb": -9.56192,
      "try": -9.61406,
      "twd": -11.09672,
      "uah": -10.09925,
      "usd": -10.42795,
      "vef": -10.42795,
      "vnd": -10.04536,
      "xag": -11.19295,
      "xau": -10.55177,
      "xdr": -10.28148,
      "xlm": -0.83234,
      "xrp": -6.45179,
      "yfi": -1.56448,
      "zar": -8.83048,
      "bits": -7.1319,
      "link": 1.04129,
      "sats": -7.1319
    },
    "price_change_percentage_14d_in_currency": {
      "aed": -7.01026,
      "ars": -10.37095,
      "aud": -6.76341,
      "bch": -19.06693,
      "bdt": -6.92286,
      "bhd": -6.97017,
      "bmd": -6.99484,
      "bnb": -3.56823,
      "brl": -9.41523,
      "btc": -6.84747,
      "cad": -6.74428,
      "chf": -6.84842,
      "clp": -6.48825,
      "cny": -6.88217,
      "czk": -7.26046,
      "dkk": -7.29864,
      "dot": 3.79402,
      "eos": 16.58013,
      "eth": -3.52474,
      "eur": -7.29289,
      "gbp": -5.93105,
      "gel": -7.67371,
      "hkd": -6.94712,
      "huf": -7.20879,
      "idr": -6.51116,
      "ils": -7.38107,
      "inr": -6.24446,
      "jpy": -5.54859,
      "krw": -5.07797,
      "kwd": -6.97541,
      "lkr": -6.64114,
      "ltc": -2.70467,
      "mmk": -6.99484,
      "mxn": -7.65191,
      "myr": -6.57802,
      "ngn": -8.96601,
      "nok": -8.01009,
      "nzd": -6.35331,
      "php": -4.19266,
      "pkr": -6.52905,
      "pln": -7.39389,
      "rub": -7.8786,
      "sar": -6.9629,
      "sek": -6.16462,
      "sgd": -6.8355,
      "sol": -1.9386,
      "thb": -6.33269,
      "try": -6.48034,
      "twd": -7.91788,
      "uah": -6.45469,
      "usd": -6.99484,
      "vef": -6.99484,
      "vnd": -6.84691,
      "xag": -12.39785,
      "xau": -7.06073,
      "xdr": -7.96279,
      "xlm": -0.89775,
      "xrp": -5.07715,
      "yfi": -3.70129,
      "zar": -5.917,
      "bits": -6.84747,
      "link": -2.106,
      "sats": -6.84747
    },
    "price_change_percentage_30d_in_currency": {
      "aed": -18.152,
      "ars": -17.86935,
      "aud": -18.64854,
      "bch": -29.33687,
      "bdt": -17.64661,
      "bhd": -18.10779,
      "bmd": -18.13863,
      "bnb": -17.12465,
      "brl": -20.45259,
      "btc": -16.68995,
      "cad": -19.6072,
      "chf": -19.56696,
      "clp": -17.949,
      "cny": -18.4573,
      "czk": -19.85546,
      "dkk": -19.68274,
      "dot": 5.40667,
      "eos": 24.68277,
      "eth": -17.44794,
      "eur": -19.67185,
      "gbp": -18.35875,
      "gel": -18.73616,
      "hkd": -17.86228,
      "huf": -19.46325,
      "idr": -18.45853,
      "ils": -19.78457,
      "inr": -17.04617,
      "jpy": -17.99748,
      "krw": -18.66101,
      "kwd": -18.39376,
      "lkr": -18.03678,
      "ltc": -4.28941,
      "mmk": -18.13863,
      "mxn": -19.24219,
      "myr": -18.70181,
      "ngn": -21.26627,
      "nok": -20.61322,
      "nzd": -19.10429,
      "php": -15.84625,
      "pkr": -17.89788,
      "pln": -19.25103,
      "rub": -20.41848,
      "sar": -18.10657,
      "sek": -18.22987,
      "sgd": -18.58713,
      "sol": -4.53522,
      "thb": -19.14834,
      "try": -16.6429,
      "twd": -19.78212,
      "uah": -18.03261,
      "usd": -18.13863,
      "vef": -18.13863,
      "vnd": -17.58356,
      "xag": -27.82176,
      "xau": -21.89628,
      "xdr": -20.38424,
      "xlm": -6.1188,
      "xrp": -9.26406,
      "yfi": -9.12896,
      "zar": -18.36048,
      "bits": -16.68995,
      "link": -0.10771,
      "sats": -16.68995
    },
    "price_change_percentage_60d_in_currency": {
      "aed": -10.27756,
      "ars": -9.92541,
      "aud": -11.56329,
      "bch": -33.54355,
      "bdt": -9.66176,
      "bhd": -10.20991,
      "bmd": -10.26253,
      "bnb": -17.25521,
      "brl": -15.22837,
      "btc": -26.87099,
      "cad": -11.08072,
      "chf": -10.08689,
      "clp": -12.5253,
      "cny": -11.55894,
      "czk": -11.75732,
      "dkk": -10.9858,
      "dot": -2.98254,
      "eos": 13.90799,
      "eth": -42.29178,
      "eur": -10.89669,
      "gbp": -11.12438,
      "gel": -11.27375,
      "hkd": -9.26587,
      "huf": -11.97041,
      "idr": -12.91855,
      "ils": -15.52409,
      "inr": -9.00885,
      "jpy": -8.52687,
      "krw": -12.42322,
      "kwd": -10.31463,
      "lkr": -9.6526,
      "ltc": -19.07075,
      "mmk": -10.26253,
      "mxn": -13.25116,
      "myr": -13.2962,
      "ngn": -13.42622,
      "nok": -14.32903,
      "nzd": -10.52724,
      "php": -9.34014,
      "pkr": -9.29574,
      "pln": -10.97132,
      "rub": -14.27647,
      "sar": -10.25535,
      "sek": -9.77317,
      "sgd": -11.81485,
      "sol": -13.23693,
      "thb": -11.78634,
      "try": -6.68731,
      "twd": -18.38699,
      "uah": -9.42582,
      "usd": -10.26253,
      "vef": -10.26253,
      "vnd": -9.41019,
      "xag": -20.38807,
      "xau": -11.77275,
      "xdr": -11.3591,
      "xlm": -11.54036,
      "xrp": -13.21653,
      "yfi": -17.88322,
      "zar": -13.96766,
      "bits": -26.87099,
      "link": -11.26446,
      "sats": -26.87099
    },
    "price_change_percentage_200d_in_currency": {
      "aed": -38.29855,
      "ars": -30.21745,
      "aud": -38.04627,
      "bch": -30.33834,
      "bdt": -36.75198,
      "bhd": -38.24473,
      "bmd": -38.28796,
      "bnb": -37.34367,
      "brl": -43.32191,
      "btc": -43.24993,
      "cad": -39.59747,
      "chf": -42.54612,
      "clp": -40.22643,
      "cny": -38.72513,
      "czk": -43.99916,
      "dkk": -42.99641,
      "dot": 51.37865,
      "eos": 12.14698,
      "eth": -9.01896,
      "eur": -43.00444,
      "gbp": -41.32198,
      "gel": -40.31758,
      "hkd": -37.74698,
      "huf": -44.29943,
      "idr": -36.22543,
      "ils": -41.0721,
      "inr": -36.81739,
      "jpy": -40.19085,
      "krw": -38.78683,
      "kwd": -38.46609,
      "lkr": -36.11729,
      "ltc": -26.13262,
      "mmk": -38.28796,
      "mxn": -42.26433,
      "myr": -40.87723,
      "ngn": -43.1778,
      "nok": -44.13927,
      "nzd": -38.97627,
      "php": -39.6825,
      "pkr": -36.97918,
      "pln": -43.33173,
      "rub": -54.75293,
      "sar": -38.36438,
      "sek": -45.2477,
      "sgd": -40.64807,
      "sol": 1.14899,
      "thb": -40.89345,
      "try": -29.6547,
      "twd": -43.75579,
      "uah": -38.0499,
      "usd": -38.28796,
      "vef": -38.28796,
      "vnd": -36.37426,
      "xag": -48.44744,
      "xau": -51.56477,
      "xdr": -42.66853,
      "xlm": 22.51586,
      "xrp": -46.10698,
      "yfi": -2.58647,
      "zar": -38.34442,
      "bits": -43.24993,
      "link": -12.11573,
      "sats": -43.24993
    },
    "price_change_percentage_1y_in_currency": {
      "aed": -34.84418,
      "ars": -17.81916,
      "aud": -32.98247,
      "bch": -44.37855,
      "bdt": -32.08339,
      "bhd": -34.79946,
      "bmd": -34.833,
      "bnb": -40.0322,
      "brl": -34.29168,
      "btc": -59.52,
      "cad": -34.83723,
      "chf": -39.53794,
      "clp": -34.28893,
      "cny": -35.42038,
      "czk": -38.92707,
      "dkk": -38.89416,
      "dot": 5.30627,
      "eos": -28.15463,
      "eth": -8.78961,
      "eur": -38.88756,
      "gbp": -38.15267,
      "gel": -37.58654,
      "hkd": -34.48782,
      "huf": -37.40607,
      "idr": -34.93292,
      "ils": -39.16358,
      "inr": -32.33094,
      "jpy": -40.04637,
      "krw": -34.55358,
      "kwd": -34.88676,
      "lkr": -35.72259,
      "ltc": -43.18946,
      "mmk": -34.7842,
      "mxn": -32.53967,
      "myr": -41.05487,
      "ngn": -32.3776,
      "nok": -38.3737,
      "nzd": -33.21368,
      "php": -36.30181,
      "pkr": -33.575,
      "pln": -39.77477,
      "rub": -40.34268,
      "sar": -34.82507,
      "sek": -39.60094,
      "sgd": -37.85721,
      "sol": -38.19619,
      "thb": -41.75911,
      "try": -21.10285,
      "twd": -40.48372,
      "uah": -33.09231,
      "usd": -34.833,
      "vef": -34.833,
      "vnd": -33.09133,
      "xag": -47.56076,
      "xau": -55.02211,
      "xdr": -38.98848,
      "xlm": -76.03445,
      "xrp": -85.11889,
      "yfi": -24.01224,
      "zar": -34.82716,
      "bits": -59.52,
      "link": -29.49511,
      "sats": -59.52
    },
    "market_cap_change_24h_in_currency": {
      "aed": 260128423,
      "ars": 33159447894,
      "aud": 109093195,
      "bch": 309756,
      "bdt": 8637758332,
      "bhd": 26944617,
      "bmd": 70867373,
      "bnb": 160059,
      "brl": 369929776,
      "btc": 699.405,
      "cad": 107414479,
      "chf": 66737042,
      "clp": 66524675291,
      "cny": 517843815,
      "czk": 1704887479,
      "dkk": 520755577,
      "dot": 43920270,
      "eos": 124321426,
      "eth": 30656,
      "eur": 69597194,
      "gbp": 58144790,
      "gel": 192759256,
      "hkd": 556174866,
      "huf": 26791120093,
      "idr": 1280524053633,
      "ils": 145069982,
      "inr": 6632358148,
      "jpy": 10259667774,
      "krw": 127936538066,
      "kwd": 21623228,
      "lkr": 20505404374,
      "ltc": 909860,
      "mmk": 148679749303,
      "mxn": 1503618230,
      "myr": 321683393,
      "ngn": 117447560814,
      "nok": 856423180,
      "nzd": 135110257,
      "php": 5184155030,
      "pkr": 20461050665,
      "pln": 293249354,
      "rub": 5566546384,
      "sar": 266820626,
      "sek": 964014121,
      "sgd": 96892689,
      "sol": 720673,
      "thb": 2694384559,
      "try": 2815140468,
      "twd": 2270530748,
      "uah": 3286881369,
      "usd": 70867373,
      "vef": 7095950,
      "vnd": 1955342556185,
      "xag": 2647627,
      "xau": 20567,
      "xdr": 55149143,
      "xlm": 333168641,
      "xrp": 32982863,
      "yfi": 15610,
      "zar": 1383704226,
      "bits": 699404622,
      "link": 4443218,
      "sats": 69940462219
    },
    "market_cap_change_percentage_24h_in_currency": {
      "aed": 2.99962,
      "ars": 1.20794,
      "aud": 2.99681,
      "bch": 6.20666,
      "bdt": 2.99211,
      "bhd": 3.02649,
      "bmd": 3.00108,
      "bnb": 4.41275,
      "brl": 2.85111,
      "btc": 3.10161,
      "cad": 3.32732,
      "chf": 3.46185,
      "clp": 2.98621,
      "cny": 3.05124,
      "czk": 3.34304,
      "dkk": 3.39963,
      "dot": 6.94141,
      "eos": 2.66912,
      "eth": 3.27011,
      "eur": 3.38869,
      "gbp": 3.30831,
      "gel": 3.00108,
      "hkd": 3.00043,
      "huf": 3.22836,
      "idr": 3.32419,
      "ils": 1.74894,
      "inr": 3.25084,
      "jpy": 2.99345,
      "krw": 3.94962,
      "kwd": 2.98797,
      "lkr": 2.88842,
      "ltc": 3.26829,
      "mmk": 3.00108,
      "mxn": 3.35179,
      "myr": 3.20721,
      "ngn": 3.22266,
      "nok": 3.652,
      "nzd": 3.44671,
      "php": 3.86401,
      "pkr": 3.05903,
      "pln": 3.33839,
      "rub": 3.00293,
      "sar": 3.0116,
      "sek": 4.27499,
      "sgd": 3.19177,
      "sol": 4.50157,
      "thb": 3.49672,
      "try": 3.01585,
      "twd": 3.25644,
      "uah": 3.35125,
      "usd": 3.00108,
      "vef": 3.00108,
      "vnd": 3.1739,
      "xag": 4.15807,
      "xau": 2.93853,
      "xdr": 3.30211,
      "xlm": 3.54989,
      "xrp": 3.0149,
      "yfi": 3.32701,
      "zar": 3.25606,
      "bits": 3.10161,
      "link": 2.45118,
      "sats": 3.10161
    },
    "total_supply": 10000000000.0,
    "max_supply": 10000000000.0,
    "max_supply_infinite": false,
    "circulating_supply": 3159107529.0,
    "last_updated": "2025-06-19T02:26:28.266Z"
  },
  "status_updates": [],
  "last_updated": "2025-06-19T02:26:28.266Z"
}